{
  "title": "São Paulo",
  "photo": "https://ingressorapido.github.io/images/cities/sao-paulo.png",
  "description": "A Ingresso Rápido vai te ajudar a ficar por dentro de tudo o que há de melhor em São Paulo. Confira e divirta-se!",
  "events": [
    {
      "id": 47540,
      "name": "We Will Rock You - O Musical do Queen",
      "city": "São Paulo",
      "state": "SP",
      "genre": "Teatro"
    },
    {
      "id": 48292,
      "name": "Histeria",
      "city": "São Paulo",
      "state": "SP",
      "genre": "Teatro"
    },
    {
      "id": 49135,
      "name": "Meu Passado Não Me Condena",
      "city": "São Paulo",
      "state": "SP",
      "genre": "Teatro"
    },
    {
      "id": 45955,
      "name": "Um Bonde Chamado Desejo",
      "city": "São Paulo",
      "state": "SP",
      "genre": "Teatro"
    },
    {
      "id": 45978,
      "name": "Maurício Meirelles em Perdendo Amigos",
      "city": "São Paulo",
      "state": "SP",
      "genre": "Teatro"
    },
    {
      "id": 48228,
      "name": "Whindersson Nunes",
      "city": "São Paulo",
      "state": "SP",
      "genre": "Teatro"
    },
    {
      "id": 49568,
      "name": "Russian State Ballet",
      "city": "São Paulo",
      "state": "SP",
      "genre": "Dança"
    },
    {
      "id": 48198,
      "name": "Contrações",
      "city": "São Paulo",
      "state": "SP",
      "genre": "Teatro"
    },
    {
      "id": 46924,
      "name": "Cia. Barbixas apresenta: Improvável",
      "city": "São Paulo",
      "state": "SP",
      "genre": "Teatro"
    },
    {
      "id": 48360,
      "name": "Thiago Ventura em Isso é Tudo que Eu Tenho",
      "city": "São Paulo",
      "state": "SP",
      "genre": "Teatro"
    }
  ]
}
